better_stamp_processing-0.1.dev46.dist-info/licenses/LICENSE
stamp_processing/__init__.py
stamp_processing/__version__.py
stamp_processing/detector.py
stamp_processing/preprocess.py
stamp_processing/remover.py
stamp_processing/utils.py
stamp_processing/module/__init__.py
stamp_processing/module/unet.py
stamp_processing/module/yolov5/__init__.py
stamp_processing/module/yolov5/hubconf.py
stamp_processing/module/yolov5/models/__init__.py
stamp_processing/module/yolov5/models/common.py
stamp_processing/module/yolov5/models/experimental.py
stamp_processing/module/yolov5/models/yolo.py
stamp_processing/module/yolov5/utils/__init__.py
stamp_processing/module/yolov5/utils/autoanchor.py
stamp_processing/module/yolov5/utils/datasets.py
stamp_processing/module/yolov5/utils/general.py
stamp_processing/module/yolov5/utils/torch_utils.py
tests/unit/__init__.py
tests/unit/test_detector.py
tests/unit/test_preprocess.py
tests/unit/test_remover.py
tests/unit/test_utils.py
better_stamp_processing-0.1.dev46.dist-info/METADATA
better_stamp_processing-0.1.dev46.dist-info/WHEEL
better_stamp_processing-0.1.dev46.dist-info/top_level.txt
better_stamp_processing-0.1.dev46.dist-info/RECORD
