Metadata-Version: 2.4
Name: better_stamp_processing
Version: 0.1.dev46
Summary: Stamp processing package
Home-page: https://github.com/mSounak/stamp_processing/
Author: Sun* AI Research Team
Author-email: sun.converter.team@gmail.com
Project-URL: Bug Tracker, https://github.com/mSounak/stamp_processing/issues
Classifier: Programming Language :: Python :: 3
Classifier: Programming Language :: Python :: 3.8
Classifier: Programming Language :: Python :: 3.9
Classifier: Programming Language :: Python :: 3.10
Classifier: Programming Language :: Python :: 3.11
Classifier: Programming Language :: Python :: 3.12
Classifier: Operating System :: OS Independent
Classifier: Intended Audience :: Developers
Classifier: License :: OSI Approved :: MIT License
Classifier: Topic :: Scientific/Engineering :: Image Processing
Requires-Python: >=3.8
License-File: LICENSE
Requires-Dist: gdown>=4.7.1
Requires-Dist: Pillow>=10.0.0
Requires-Dist: opencv-python>=4.8.0
Requires-Dist: torch>=2.0.0
Requires-Dist: torchvision>=0.15.0
Requires-Dist: fastai>=2.7.0
Requires-Dist: numpy>=1.21.0
Requires-Dist: PyYAML>=6.0
Requires-Dist: setuptools>=65.0.0
Dynamic: author
Dynamic: author-email
Dynamic: classifier
Dynamic: description
Dynamic: description-content-type
Dynamic: home-page
Dynamic: license-file
Dynamic: project-url
Dynamic: requires-dist
Dynamic: requires-python
Dynamic: summary
